LICENSE
drizm_commons/__init__.py
drizm_commons/google/__init__.py
drizm_commons/google/testing.py
drizm_commons/google/token.py
drizm_commons/inspect.py
drizm_commons/sqla/__init__.py
drizm_commons/sqla/base.py
drizm_commons/sqla/conn.py
drizm_commons/sqla/encode.py
drizm_commons/sqla/inspect.py
drizm_commons/testing/__init__.py
drizm_commons/testing/biased.py
drizm_commons/testing/conversion.py
drizm_commons/testing/faker.py
drizm_commons/testing/truthiness.py
drizm_commons/utils/__init__.py
drizm_commons/utils/decorators.py
drizm_commons/utils/pathing.py
drizm_commons/utils/tf.py
drizm_commons/utils/type.py
drizm_commons/utils/various.py
drizm_commons-0.5.0.dist-info/LICENSE
drizm_commons-0.5.0.dist-info/WHEEL
drizm_commons-0.5.0.dist-info/METADATA
drizm_commons-0.5.0.dist-info/RECORD
