Metadata-Version: 2.1
Name: drizm-commons
Version: 0.5.0
Summary: Python3 commons for the Drizm organization
Home-page: https://github.com/drizm-team/python-commons
License: MIT
Keywords: commons,sqlalchemy
Author: ThaRising
Author-email: kochbe.ber@gmail.com
Maintainer: Dominik Lewandowski
Maintainer-email: dominik.lewandow@gmail.com
Requires-Python: >=3.8,<4.0
Classifier: Environment :: Web Environment
Classifier: Intended Audience :: Developers
Classifier: License :: OSI Approved :: MIT License
Classifier: Programming Language :: Python :: 3
Classifier: Programming Language :: Python :: 3 :: Only
Classifier: Programming Language :: Python :: 3.8
Provides-Extra: all
Provides-Extra: google
Provides-Extra: sqla
Requires-Dist: Pillow (>=8.0.1,<9.0.0)
Requires-Dist: google-auth (==1.23.0); extra == "google" or extra == "all"
Requires-Dist: google-cloud-storage (==1.35.0); extra == "google" or extra == "all"
Requires-Dist: requests (>=2.25.0,<3.0.0); extra == "google" or extra == "all"
Requires-Dist: sqlalchemy (==1.3.20); extra == "sqla" or extra == "all"
Project-URL: Repository, https://github.com/drizm-team/python-commons
